{
	"info": {
		"_postman_id": "1d632529-d93b-4ce9-8d90-c1630eaebf91",
		"name": "app-ventas-service",
		"schema": "https://schema.getpostman.com/json/collection/v2.1.0/collection.json",
		"_exporter_id": "9826788"
	},
	"item": [
		{
			"name": "Categoria",
			"item": [
				{
					"name": "categorias/listar-todo",
					"request": {
						"method": "GET",
						"header": [],
						"url": {
							"raw": "http://localhost:8080/categorias",
							"protocol": "http",
							"host": [
								"localhost"
							],
							"port": "8080",
							"path": [
								"categorias"
							]
						}
					},
					"response": []
				},
				{
					"name": "categorias/{id}",
					"protocolProfileBehavior": {
						"disableBodyPruning": true
					},
					"request": {
						"method": "GET",
						"header": [],
						"body": {
							"mode": "raw",
							"raw": "",
							"options": {
								"raw": {
									"language": "json"
								}
							}
						},
						"url": {
							"raw": "http://localhost:8080/categorias/1",
							"protocol": "http",
							"host": [
								"localhost"
							],
							"port": "8080",
							"path": [
								"categorias",
								"1"
							]
						}
					},
					"response": []
				},
				{
					"name": "categorias/actualizar",
					"request": {
						"method": "PUT",
						"header": [],
						"body": {
							"mode": "raw",
							"raw": "    {\r\n        \"idCategoria\": 4,\r\n        \"nombre\": \"Limpieza\",\r\n        \"descripcion\": \"Limpieza\"\r\n    }",
							"options": {
								"raw": {
									"language": "json"
								}
							}
						},
						"url": {
							"raw": "http://localhost:8080/categorias",
							"protocol": "http",
							"host": [
								"localhost"
							],
							"port": "8080",
							"path": [
								"categorias"
							]
						}
					},
					"response": []
				},
				{
					"name": "categorias",
					"request": {
						"method": "POST",
						"header": [],
						"body": {
							"mode": "raw",
							"raw": "{\r\n    \"nombre\": \"categoria 2\",\r\n    \"descripcion\": \"categoria 2\"\r\n}",
							"options": {
								"raw": {
									"language": "json"
								}
							}
						},
						"url": {
							"raw": "http://localhost:8080/categorias",
							"protocol": "http",
							"host": [
								"localhost"
							],
							"port": "8080",
							"path": [
								"categorias"
							]
						}
					},
					"response": []
				},
				{
					"name": "categorias/buscar-por-filtro",
					"request": {
						"method": "POST",
						"header": [],
						"body": {
							"mode": "raw",
							"raw": "    {\r\n        \"nombre\": \"Regalos\",\r\n        \"descripcion\": \"Regalos\"\r\n    }",
							"options": {
								"raw": {
									"language": "json"
								}
							}
						},
						"url": {
							"raw": "http://localhost:8080/categorias/buscar-por-filtro",
							"protocol": "http",
							"host": [
								"localhost"
							],
							"port": "8080",
							"path": [
								"categorias",
								"buscar-por-filtro"
							]
						}
					},
					"response": []
				},
				{
					"name": "categorias/{id}",
					"request": {
						"method": "DELETE",
						"header": [],
						"body": {
							"mode": "raw",
							"raw": "",
							"options": {
								"raw": {
									"language": "json"
								}
							}
						},
						"url": {
							"raw": "http://localhost:8080/categorias/4",
							"protocol": "http",
							"host": [
								"localhost"
							],
							"port": "8080",
							"path": [
								"categorias",
								"4"
							]
						}
					},
					"response": []
				}
			]
		},
		{
			"name": "Presentacion",
			"item": [
				{
					"name": "presentaciones/listar-todo",
					"request": {
						"method": "GET",
						"header": [],
						"url": {
							"raw": "http://localhost:8080/presentaciones",
							"protocol": "http",
							"host": [
								"localhost"
							],
							"port": "8080",
							"path": [
								"presentaciones"
							]
						}
					},
					"response": []
				},
				{
					"name": "presentaciones/{id}",
					"protocolProfileBehavior": {
						"disableBodyPruning": true
					},
					"request": {
						"method": "GET",
						"header": [],
						"body": {
							"mode": "raw",
							"raw": "",
							"options": {
								"raw": {
									"language": "json"
								}
							}
						},
						"url": {
							"raw": "http://localhost:8080/presentaciones/1",
							"protocol": "http",
							"host": [
								"localhost"
							],
							"port": "8080",
							"path": [
								"presentaciones",
								"1"
							]
						}
					},
					"response": []
				},
				{
					"name": "presentaciones",
					"request": {
						"method": "PUT",
						"header": [],
						"body": {
							"mode": "raw",
							"raw": "    {\r\n        \"idPresentacion\": 3,\r\n        \"nombre\": \"Presentacion 3\",\r\n        \"descripcion\": \"Presentacion 3\"\r\n    }",
							"options": {
								"raw": {
									"language": "json"
								}
							}
						},
						"url": {
							"raw": "http://localhost:8080/presentaciones",
							"protocol": "http",
							"host": [
								"localhost"
							],
							"port": "8080",
							"path": [
								"presentaciones"
							]
						}
					},
					"response": []
				},
				{
					"name": "presentaciones",
					"request": {
						"method": "POST",
						"header": [],
						"body": {
							"mode": "raw",
							"raw": "{\r\n    \"nombre\": \"Presentacion 1\",\r\n    \"descripcion\": \"Presentacion 1\"\r\n}",
							"options": {
								"raw": {
									"language": "json"
								}
							}
						},
						"url": {
							"raw": "http://localhost:8080/presentaciones",
							"protocol": "http",
							"host": [
								"localhost"
							],
							"port": "8080",
							"path": [
								"presentaciones"
							]
						}
					},
					"response": []
				},
				{
					"name": "presentaciones/buscar-por-filtro",
					"request": {
						"method": "POST",
						"header": [],
						"body": {
							"mode": "raw",
							"raw": "    {\r\n        \"nombre\": \"Limpieza\",\r\n        \"descripcion\": \"Limpieza\"\r\n    }",
							"options": {
								"raw": {
									"language": "json"
								}
							}
						},
						"url": {
							"raw": "http://localhost:8080/presentaciones/buscar-por-filtro",
							"protocol": "http",
							"host": [
								"localhost"
							],
							"port": "8080",
							"path": [
								"presentaciones",
								"buscar-por-filtro"
							]
						}
					},
					"response": []
				},
				{
					"name": "presentaciones/{id}",
					"request": {
						"method": "DELETE",
						"header": [],
						"body": {
							"mode": "raw",
							"raw": "",
							"options": {
								"raw": {
									"language": "json"
								}
							}
						},
						"url": {
							"raw": "http://localhost:8080/presentaciones/1",
							"protocol": "http",
							"host": [
								"localhost"
							],
							"port": "8080",
							"path": [
								"presentaciones",
								"1"
							]
						}
					},
					"response": []
				}
			]
		},
		{
			"name": "Login",
			"item": [
				{
					"name": "oauth/token",
					"request": {
						"method": "GET",
						"header": []
					},
					"response": []
				}
			]
		}
	]
}